Body_Tracking/__init__.py
Body_Tracking/body_tracking_module.py
Face_Tracking/__init__.py
Face_Tracking/face_mesh_detection_module.py
Face_Tracking/face_tracking_module.py
Hand_Tacking/__init__.py
Hand_Tacking/hand_tracking_module.py
pose_estimation_mp-0.1.5.data/scripts/pose_estimation_mp
pose_estimation_mp-0.1.5.dist-info/LICENSE
pose_estimation_mp-0.1.5.dist-info/METADATA
pose_estimation_mp-0.1.5.dist-info/WHEEL
pose_estimation_mp-0.1.5.dist-info/top_level.txt
pose_estimation_mp-0.1.5.dist-info/RECORD
