Metadata-Version: 2.1
Name: pose-estimation-mp
Version: 0.1.5
Summary: A Body, Hand, Face tracking utility
Home-page: https://github.com/REZ3LIET/Pose_Estimations
Author: Samar Kale
Author-email: rz.samar.kale@gmail.com
License: UNKNOWN
Platform: UNKNOWN
Classifier: Programming Language :: Python :: 3
Classifier: License :: OSI Approved :: MIT License
Classifier: Operating System :: OS Independent
License-File: LICENSE
Requires-Dist: mediapipe
Requires-Dist: opencv-python
